yodi/__init__.py
yodi/yodi.py
yodi_pys-0.1.0.dist-info/LICENSE
yodi_pys-0.1.0.dist-info/METADATA
yodi_pys-0.1.0.dist-info/WHEEL
yodi_pys-0.1.0.dist-info/top_level.txt
yodi_pys-0.1.0.dist-info/RECORD
