Metadata-Version: 2.1
Name: yodi_pys
Version: 0.1.0
Author: Yodi Dev Team
Author-email: djdefodji@gmail.com
Classifier: Programming Language :: Python :: 3
Classifier: License :: OSI Approved :: MIT License
Classifier: Operating System :: OS Independent
Requires-Python: >=3.6
License-File: LICENSE
